magicpandas/__init__.py
magicpandas/chromify.py
magicpandas/context_managers.py
magicpandas/easy_xlsxwriter.py
magicpandas/frame.py
magicpandas/data/__init__.py
magicpandas/finance/__init__.py
magicpandas/finance/bc35.py
magicpandas/finance/cashflows.py
magicpandas/finance/irr.py
magicpandas/finance/shortcuts.py
magicpandas/tests/__init__.py
magicpandas/tests/fixtures.py
magicpandas/tests/test_browse.py
magicpandas/tests/test_drop.py
magicpandas/tests/test_graph.py
magicpandas/tests/test_inspect_for_django.py
magicpandas/tests/test_keep.py
magicpandas/tests/test_search_by_ranges.py
magicpandas/tests/test_search_by_wildcard.py
magicpandas/tests/test_search_iterable.py
magicpandas/tests/test_search_lazily.py
magicpandas/tests/finance/__init__.py
magicpandas/tests/finance/test_bc35.py
magicpandas/tests/finance/test_cashflows.py
magicpandas/tests/finance/test_irr.py
magicpandas/tests/finance/test_magicframe_methods.py
magicpandas/utils/__init__.py
magicpandas/utils/search.py
magicpandas-0.0.4.dist-info/LICENSE
magicpandas-0.0.4.dist-info/METADATA
magicpandas-0.0.4.dist-info/WHEEL
magicpandas-0.0.4.dist-info/top_level.txt
magicpandas-0.0.4.dist-info/RECORD
