Metadata-Version: 2.1
Name: magicpandas
Version: 0.0.4
Summary: A dead simple interface for manipulating pandas dataframes
Home-page: https://github.com/pandichef/magicpandas
Author: pandichef
License: UNKNOWN
Platform: UNKNOWN
Classifier: Development Status :: 3 - Alpha
Classifier: Intended Audience :: Developers
Classifier: Topic :: Software Development :: Build Tools
Classifier: License :: OSI Approved :: MIT License
Classifier: Programming Language :: Python :: 3.6
Classifier: Programming Language :: Python :: 3.7
Classifier: Programming Language :: Python :: 3.8
Requires-Python: >=2.7, !=3.0.*, !=3.1.*, !=3.2.*, !=3.3.*, !=3.4.*, <4
Requires-Dist: altair
Requires-Dist: numpy-financial
Requires-Dist: pandas
Requires-Dist: pandas-market-calendars
Requires-Dist: statsmodels
Requires-Dist: xlsxwriter
Provides-Extra: dev
Requires-Dist: vega-datasets ; extra == 'dev'
Requires-Dist: pytest ; extra == 'dev'
Requires-Dist: ipython ; extra == 'dev'
Requires-Dist: pytest-cov ; extra == 'dev'
Requires-Dist: pipenv-setup ; extra == 'dev'
